{
  "canvas": {
    "version": "2.2.11",
    "width": 3100,
    "height": 3100,
    "scrollTop": -58.8000014019011,
    "scrollLeft": -1426.003145284653,
    "zoomLevel": 1,
    "show": {
      "tableComment": true,
      "columnComment": true,
      "columnDataType": true,
      "columnDefault": true,
      "columnAutoIncrement": false,
      "columnPrimaryKey": true,
      "columnUnique": false,
      "columnNotNull": true,
      "relationship": true
    },
    "database": "PostgreSQL",
    "databaseName": "",
    "canvasType": "ERD",
    "language": "GraphQL",
    "tableCase": "pascalCase",
    "columnCase": "camelCase",
    "highlightTheme": "VS2015",
    "bracketType": "none",
    "setting": {
      "relationshipDataTypeSync": true,
      "relationshipOptimization": false,
      "columnOrder": [
        "columnName",
        "columnDataType",
        "columnNotNull",
        "columnUnique",
        "columnAutoIncrement",
        "columnDefault",
        "columnComment"
      ]
    },
    "pluginSerializationMap": {}
  },
  "table": {
    "tables": [
      {
        "name": "ophthalmologymedicationdm",
        "comment": "",
        "columns": [
          {
            "id": "5839962f-5304-4f8f-9d8d-8750d8795d84",
            "name": "medication_id",
            "comment": "",
            "dataType": "integer",
            "default": "",
            "option": {
              "autoIncrement": false,
              "primaryKey": true,
              "unique": false,
              "notNull": true
            },
            "ui": {
              "active": false,
              "pk": true,
              "fk": false,
              "pfk": false,
              "widthName": 87.43608093261719,
              "widthComment": 60,
              "widthDataType": 60,
              "widthDefault": 60
            }
          },
          {
            "id": "1bcec6c0-88f1-4834-a23f-7e0f6644f1db",
            "name": "med_cat",
            "comment": "",
            "dataType": "character",
            "default": "",
            "option": {
              "autoIncrement": false,
              "primaryKey": false,
              "unique": false,
              "notNull": false
            },
            "ui": {
              "active": false,
              "pk": false,
              "fk": false,
              "pfk": false,
              "widthName": 60,
              "widthComment": 60,
              "widthDataType": 60,
              "widthDefault": 60
            }
          },
          {
            "id": "9150431f-882f-478f-b693-2a701f8d1d0f",
            "name": "med_subcat",
            "comment": "",
            "dataType": "character",
            "default": "",
            "option": {
              "autoIncrement": false,
              "primaryKey": false,
              "unique": false,
              "notNull": false
            },
            "ui": {
              "active": false,
              "pk": false,
              "fk": false,
              "pfk": false,
              "widthName": 75.73606872558594,
              "widthComment": 60,
              "widthDataType": 60,
              "widthDefault": 60
            }
          },
          {
            "id": "00c23320-452c-4edc-b0e5-46a5ef199597",
            "name": "therapeutic_class",
            "comment": "",
            "dataType": "character",
            "default": "",
            "option": {
              "autoIncrement": false,
              "primaryKey": false,
              "unique": false,
              "notNull": false
            },
            "ui": {
              "active": false,
              "pk": false,
              "fk": false,
              "pfk": false,
              "widthName": 107.22209167480469,
              "widthComment": 60,
              "widthDataType": 60,
              "widthDefault": 60
            }
          },
          {
            "id": "e9f4190e-6ae1-4fff-99b3-5e56d89ee6fe",
            "name": "pharmaceutical_class",
            "comment": "",
            "dataType": "character",
            "default": "",
            "option": {
              "autoIncrement": false,
              "primaryKey": false,
              "unique": false,
              "notNull": false
            },
            "ui": {
              "active": false,
              "pk": false,
              "fk": false,
              "pfk": false,
              "widthName": 131.79209899902344,
              "widthComment": 60,
              "widthDataType": 60,
              "widthDefault": 60
            }
          },
          {
            "id": "8173da4b-b414-4cc9-ae81-e49ff4b66b70",
            "name": "name",
            "comment": "",
            "dataType": "character",
            "default": "",
            "option": {
              "autoIncrement": false,
              "primaryKey": false,
              "unique": false,
              "notNull": false
            },
            "ui": {
              "active": false,
              "pk": false,
              "fk": false,
              "pfk": false,
              "widthName": 60,
              "widthComment": 60,
              "widthDataType": 60,
              "widthDefault": 60
            }
          },
          {
            "id": "8fcf62de-a5c0-48eb-bff9-cb3cfcd12b99",
            "name": "generic_name",
            "comment": "",
            "dataType": "character",
            "default": "",
            "option": {
              "autoIncrement": false,
              "primaryKey": false,
              "unique": false,
              "notNull": false
            },
            "ui": {
              "active": false,
              "pk": false,
              "fk": false,
              "pfk": false,
              "widthName": 88.2420654296875,
              "widthComment": 60,
              "widthDataType": 60,
              "widthDefault": 60
            }
          }
        ],
        "ui": {
          "active": false,
          "left": 2276.5367,
          "top": 143.6185,
          "zIndex": 3,
          "widthName": 183.59718322753906,
          "widthComment": 60
        },
        "visible": true,
        "id": "b04ce783-eeee-4ecc-b77f-656e1612f9b3"
      },
      {
        "name": "ophthalmologycurrentmedications",
        "comment": "",
        "columns": [
          {
            "name": "order_med_id",
            "comment": "",
            "dataType": "integer",
            "default": "",
            "option": {
              "autoIncrement": false,
              "primaryKey": false,
              "unique": false,
              "notNull": true
            },
            "ui": {
              "active": false,
              "pk": false,
              "fk": true,
              "pfk": false,
              "widthName": 86.04507446289062,
              "widthComment": 60,
              "widthDataType": 60,
              "widthDefault": 60
            },
            "id": "8949a3ff-8cac-4d31-85fc-aaa381ff06e4"
          },
          {
            "name": "medication_id",
            "comment": "",
            "dataType": "integer",
            "default": "",
            "option": {
              "autoIncrement": false,
              "primaryKey": false,
              "unique": false,
              "notNull": true
            },
            "ui": {
              "active": false,
              "pk": false,
              "fk": true,
              "pfk": false,
              "widthName": 87.43608093261719,
              "widthComment": 60,
              "widthDataType": 60,
              "widthDefault": 60
            },
            "id": "1b08257c-d324-45d6-ac2d-adfe6adece74"
          },
          {
            "id": "12bc0414-7595-4cc8-8478-71398fabf380",
            "name": "pat_enc_csn_id",
            "comment": "",
            "dataType": "integer",
            "default": "",
            "option": {
              "autoIncrement": false,
              "primaryKey": false,
              "unique": false,
              "notNull": false
            },
            "ui": {
              "active": false,
              "pk": false,
              "fk": false,
              "pfk": false,
              "widthName": 92.75308227539062,
              "widthComment": 60,
              "widthDataType": 60,
              "widthDefault": 60
            }
          },
          {
            "id": "c7b73065-5ba6-4e6d-9ee0-efa71ea6cd64",
            "name": "pat_id",
            "comment": "",
            "dataType": "character",
            "default": "",
            "option": {
              "autoIncrement": false,
              "primaryKey": false,
              "unique": false,
              "notNull": false
            },
            "ui": {
              "active": false,
              "pk": false,
              "fk": false,
              "pfk": false,
              "widthName": 60,
              "widthComment": 60,
              "widthDataType": 60,
              "widthDefault": 60
            }
          },
          {
            "id": "50abf274-3b41-4215-b6c7-a212126610e7",
            "name": "name",
            "comment": "",
            "dataType": "character",
            "default": "",
            "option": {
              "autoIncrement": false,
              "primaryKey": false,
              "unique": false,
              "notNull": false
            },
            "ui": {
              "active": false,
              "pk": false,
              "fk": false,
              "pfk": false,
              "widthName": 60,
              "widthComment": 60,
              "widthDataType": 60,
              "widthDefault": 60
            }
          },
          {
            "id": "635f4a80-0292-4ed2-8ec2-009340ad6fa1",
            "name": "generic",
            "comment": "",
            "dataType": "character",
            "default": "",
            "option": {
              "autoIncrement": false,
              "primaryKey": false,
              "unique": false,
              "notNull": false
            },
            "ui": {
              "active": false,
              "pk": false,
              "fk": false,
              "pfk": false,
              "widthName": 60,
              "widthComment": 60,
              "widthDataType": 60,
              "widthDefault": 60
            }
          },
          {
            "id": "2f56aaf2-04c8-41ae-80f6-cf4c77e1dedb",
            "name": "therapeutic_class",
            "comment": "",
            "dataType": "character",
            "default": "",
            "option": {
              "autoIncrement": false,
              "primaryKey": false,
              "unique": false,
              "notNull": false
            },
            "ui": {
              "active": false,
              "pk": false,
              "fk": false,
              "pfk": false,
              "widthName": 107.22209167480469,
              "widthComment": 60,
              "widthDataType": 60,
              "widthDefault": 60
            }
          },
          {
            "id": "5711d56e-63a1-48bb-a213-f1b5f246ebd8",
            "name": "pharmaceutical_class",
            "comment": "",
            "dataType": "character",
            "default": "",
            "option": {
              "autoIncrement": false,
              "primaryKey": false,
              "unique": false,
              "notNull": false
            },
            "ui": {
              "active": false,
              "pk": false,
              "fk": false,
              "pfk": false,
              "widthName": 131.79209899902344,
              "widthComment": 60,
              "widthDataType": 60,
              "widthDefault": 60
            }
          },
          {
            "id": "9f2d2061-7a88-4cd1-94a9-d04e257ecbbb",
            "name": "strength",
            "comment": "",
            "dataType": "character",
            "default": "",
            "option": {
              "autoIncrement": false,
              "primaryKey": false,
              "unique": false,
              "notNull": false
            },
            "ui": {
              "active": false,
              "pk": false,
              "fk": false,
              "pfk": false,
              "widthName": 60,
              "widthComment": 60,
              "widthDataType": 60,
              "widthDefault": 60
            }
          },
          {
            "id": "44382111-1663-4ae7-b217-c8ebc185959b",
            "name": "ordering_dttm",
            "comment": "",
            "dataType": "time",
            "default": "",
            "option": {
              "autoIncrement": false,
              "primaryKey": false,
              "unique": false,
              "notNull": false
            },
            "ui": {
              "active": false,
              "pk": false,
              "fk": false,
              "pfk": false,
              "widthName": 90.36109924316406,
              "widthComment": 60,
              "widthDataType": 60,
              "widthDefault": 60
            }
          },
          {
            "id": "0b040d4e-0526-462b-9051-580d18b3a49f",
            "name": "update_dttm",
            "comment": "",
            "dataType": "time",
            "default": "",
            "option": {
              "autoIncrement": false,
              "primaryKey": false,
              "unique": false,
              "notNull": false
            },
            "ui": {
              "active": false,
              "pk": false,
              "fk": false,
              "pfk": false,
              "widthName": 80.65008544921875,
              "widthComment": 60,
              "widthDataType": 60,
              "widthDefault": 60
            }
          },
          {
            "id": "6ae0d28b-f680-4ca6-b906-c8769c0d5078",
            "name": "add_to_list_tm",
            "comment": "",
            "dataType": "time",
            "default": "",
            "option": {
              "autoIncrement": false,
              "primaryKey": false,
              "unique": false,
              "notNull": false
            },
            "ui": {
              "active": false,
              "pk": false,
              "fk": false,
              "pfk": false,
              "widthName": 89.63308715820312,
              "widthComment": 60,
              "widthDataType": 60,
              "widthDefault": 60
            }
          },
          {
            "id": "00f68f7b-dadd-44c9-bd1e-33b1002cf168",
            "name": "frequency",
            "comment": "",
            "dataType": "character",
            "default": "",
            "option": {
              "autoIncrement": false,
              "primaryKey": false,
              "unique": false,
              "notNull": false
            },
            "ui": {
              "active": false,
              "pk": false,
              "fk": false,
              "pfk": false,
              "widthName": 63.17805480957031,
              "widthComment": 60,
              "widthDataType": 60,
              "widthDefault": 60
            }
          },
          {
            "id": "f3970162-1636-4555-8cb0-7119adcd9bee",
            "name": "contact_date",
            "comment": "might be updates or changes to presecription",
            "dataType": "time",
            "default": "",
            "option": {
              "autoIncrement": false,
              "primaryKey": false,
              "unique": false,
              "notNull": false
            },
            "ui": {
              "active": false,
              "pk": false,
              "fk": false,
              "pfk": false,
              "widthName": 80.14306640625,
              "widthComment": 120,
              "widthDataType": 60,
              "widthDefault": 60
            }
          }
        ],
        "ui": {
          "active": false,
          "left": 2274.4858,
          "top": 491.5381,
          "zIndex": 9,
          "widthName": 214.48521423339844,
          "widthComment": 60
        },
        "visible": true,
        "id": "c7d73d58-d408-4f7b-af3c-95283b2251c9"
      },
      {
        "name": "ophthalmologymedications",
        "comment": "",
        "columns": [
          {
            "id": "16976a4b-11a1-4d9f-b040-da5598645be4",
            "name": "order_med_id",
            "comment": "",
            "dataType": "integer",
            "default": "",
            "option": {
              "autoIncrement": false,
              "primaryKey": true,
              "unique": false,
              "notNull": true
            },
            "ui": {
              "active": false,
              "pk": true,
              "fk": false,
              "pfk": false,
              "widthName": 86.04507446289062,
              "widthComment": 60,
              "widthDataType": 60,
              "widthDefault": 60
            }
          },
          {
            "name": "medication_id",
            "comment": "",
            "dataType": "integer",
            "default": "",
            "option": {
              "autoIncrement": false,
              "primaryKey": false,
              "unique": false,
              "notNull": true
            },
            "ui": {
              "active": false,
              "pk": false,
              "fk": true,
              "pfk": false,
              "widthName": 87.43608093261719,
              "widthComment": 60,
              "widthDataType": 60,
              "widthDefault": 60
            },
            "id": "201069a0-313b-4da9-8cad-03bb203df61d"
          },
          {
            "id": "09d598f9-ac44-4b7a-bda9-08ae2f101cda",
            "name": "pat_enc_csn_id",
            "comment": "",
            "dataType": "integer",
            "default": "",
            "option": {
              "autoIncrement": false,
              "primaryKey": false,
              "unique": false,
              "notNull": false
            },
            "ui": {
              "active": false,
              "pk": false,
              "fk": false,
              "pfk": false,
              "widthName": 92.75308227539062,
              "widthComment": 60,
              "widthDataType": 60,
              "widthDefault": 60
            }
          },
          {
            "id": "ce1d7b0f-e347-46fd-abdd-5f32469da815",
            "name": "pat_id",
            "comment": "",
            "dataType": "character",
            "default": "",
            "option": {
              "autoIncrement": false,
              "primaryKey": false,
              "unique": false,
              "notNull": false
            },
            "ui": {
              "active": false,
              "pk": false,
              "fk": false,
              "pfk": false,
              "widthName": 60,
              "widthComment": 60,
              "widthDataType": 60,
              "widthDefault": 60
            }
          },
          {
            "id": "1fd91251-df40-413d-a43a-d65c03d8ad3a",
            "name": "ext_formulary_id",
            "comment": "",
            "dataType": "character",
            "default": "",
            "option": {
              "autoIncrement": false,
              "primaryKey": false,
              "unique": false,
              "notNull": false
            },
            "ui": {
              "active": false,
              "pk": false,
              "fk": false,
              "pfk": false,
              "widthName": 104.07608032226562,
              "widthComment": 60,
              "widthDataType": 60,
              "widthDefault": 60
            }
          },
          {
            "id": "a400201a-5889-43b9-b180-46701d568376",
            "name": "ext_copay_id",
            "comment": "",
            "dataType": "character",
            "default": "",
            "option": {
              "autoIncrement": false,
              "primaryKey": false,
              "unique": false,
              "notNull": false
            },
            "ui": {
              "active": false,
              "pk": false,
              "fk": false,
              "pfk": false,
              "widthName": 79.55805969238281,
              "widthComment": 60,
              "widthDataType": 60,
              "widthDefault": 60
            }
          },
          {
            "id": "15e768d2-891b-4968-8f3c-0798b39c5e0e",
            "name": "order_status",
            "comment": "",
            "dataType": "character",
            "default": "",
            "option": {
              "autoIncrement": false,
              "primaryKey": false,
              "unique": false,
              "notNull": false
            },
            "ui": {
              "active": false,
              "pk": false,
              "fk": false,
              "pfk": false,
              "widthName": 78.60906982421875,
              "widthComment": 60,
              "widthDataType": 60,
              "widthDefault": 60
            }
          },
          {
            "id": "01b8d60d-5fd1-45c6-bc80-ef141b6aa9d3",
            "name": "med_presc_prov_name",
            "comment": "",
            "dataType": "character",
            "default": "",
            "option": {
              "autoIncrement": false,
              "primaryKey": false,
              "unique": false,
              "notNull": false
            },
            "ui": {
              "active": false,
              "pk": false,
              "fk": false,
              "pfk": false,
              "widthName": 141.828125,
              "widthComment": 60,
              "widthDataType": 60,
              "widthDefault": 60
            }
          },
          {
            "id": "ecae051a-44f8-412c-82be-d41b0f61d362",
            "name": "ordering_dttm",
            "comment": "",
            "dataType": "time",
            "default": "",
            "option": {
              "autoIncrement": false,
              "primaryKey": false,
              "unique": false,
              "notNull": false
            },
            "ui": {
              "active": false,
              "pk": false,
              "fk": false,
              "pfk": false,
              "widthName": 90.36109924316406,
              "widthComment": 60,
              "widthDataType": 60,
              "widthDefault": 60
            }
          },
          {
            "id": "52314208-63e2-46d4-b93c-f7e53d358e10",
            "name": "order_start_date",
            "comment": "",
            "dataType": "time",
            "default": "",
            "option": {
              "autoIncrement": false,
              "primaryKey": false,
              "unique": false,
              "notNull": false
            },
            "ui": {
              "active": false,
              "pk": false,
              "fk": false,
              "pfk": false,
              "widthName": 102.80207824707031,
              "widthComment": 60,
              "widthDataType": 60,
              "widthDefault": 60
            }
          },
          {
            "id": "1135b9c0-76e7-4d54-9167-45bb57b914ea",
            "name": "order_end_date",
            "comment": "",
            "dataType": "time",
            "default": "",
            "option": {
              "autoIncrement": false,
              "primaryKey": false,
              "unique": false,
              "notNull": false
            },
            "ui": {
              "active": false,
              "pk": false,
              "fk": false,
              "pfk": false,
              "widthName": 97.88807678222656,
              "widthComment": 60,
              "widthDataType": 60,
              "widthDefault": 60
            }
          },
          {
            "id": "a5349375-2053-4a29-b5a8-e1d4d96833c1",
            "name": "discontinue_datetime",
            "comment": "",
            "dataType": "time",
            "default": "",
            "option": {
              "autoIncrement": false,
              "primaryKey": false,
              "unique": false,
              "notNull": false
            },
            "ui": {
              "active": false,
              "pk": false,
              "fk": false,
              "pfk": false,
              "widthName": 133.7811279296875,
              "widthComment": 60,
              "widthDataType": 60,
              "widthDefault": 60
            }
          },
          {
            "id": "d220c064-4088-44e6-8947-e74f4c2a1d60",
            "name": "name",
            "comment": "",
            "dataType": "character",
            "default": "",
            "option": {
              "autoIncrement": false,
              "primaryKey": false,
              "unique": false,
              "notNull": false
            },
            "ui": {
              "active": false,
              "pk": false,
              "fk": false,
              "pfk": false,
              "widthName": 60,
              "widthComment": 60,
              "widthDataType": 60,
              "widthDefault": 60
            }
          },
          {
            "id": "3496e6b8-5034-4bb0-b371-7d77d4c7f33d",
            "name": "generic",
            "comment": "",
            "dataType": "character",
            "default": "",
            "option": {
              "autoIncrement": false,
              "primaryKey": false,
              "unique": false,
              "notNull": false
            },
            "ui": {
              "active": false,
              "pk": false,
              "fk": false,
              "pfk": false,
              "widthName": 60,
              "widthComment": 60,
              "widthDataType": 60,
              "widthDefault": 60
            }
          },
          {
            "id": "a62e68af-b197-46f6-9dcf-be1eeab4b28c",
            "name": "therapeutic_class",
            "comment": "",
            "dataType": "character",
            "default": "",
            "option": {
              "autoIncrement": false,
              "primaryKey": false,
              "unique": false,
              "notNull": false
            },
            "ui": {
              "active": false,
              "pk": false,
              "fk": false,
              "pfk": false,
              "widthName": 107.22209167480469,
              "widthComment": 60,
              "widthDataType": 60,
              "widthDefault": 60
            }
          },
          {
            "id": "d8dab197-2d88-450e-985c-42a6dda0adb2",
            "name": "pharmaceutical_class",
            "comment": "",
            "dataType": "character",
            "default": "",
            "option": {
              "autoIncrement": false,
              "primaryKey": false,
              "unique": false,
              "notNull": false
            },
            "ui": {
              "active": false,
              "pk": false,
              "fk": false,
              "pfk": false,
              "widthName": 131.79209899902344,
              "widthComment": 60,
              "widthDataType": 60,
              "widthDefault": 60
            }
          },
          {
            "id": "25356038-1b5e-4334-a8a6-36af5255dba0",
            "name": "strength",
            "comment": "",
            "dataType": "character",
            "default": "",
            "option": {
              "autoIncrement": false,
              "primaryKey": false,
              "unique": false,
              "notNull": false
            },
            "ui": {
              "active": false,
              "pk": false,
              "fk": false,
              "pfk": false,
              "widthName": 60,
              "widthComment": 60,
              "widthDataType": 60,
              "widthDefault": 60
            }
          },
          {
            "id": "2765ca40-6a2d-4dd0-b361-eeb9b6254964",
            "name": "med_dose_unit",
            "comment": "",
            "dataType": "character",
            "default": "",
            "option": {
              "autoIncrement": false,
              "primaryKey": false,
              "unique": false,
              "notNull": false
            },
            "ui": {
              "active": false,
              "pk": false,
              "fk": false,
              "pfk": false,
              "widthName": 94.56008911132812,
              "widthComment": 60,
              "widthDataType": 60,
              "widthDefault": 60
            }
          },
          {
            "id": "3af66613-59ba-4c3f-b327-4948286db858",
            "name": "admin_dose_unit",
            "comment": "",
            "dataType": "character",
            "default": "",
            "option": {
              "autoIncrement": false,
              "primaryKey": false,
              "unique": false,
              "notNull": false
            },
            "ui": {
              "active": false,
              "pk": false,
              "fk": false,
              "pfk": false,
              "widthName": 105.90910339355469,
              "widthComment": 60,
              "widthDataType": 60,
              "widthDefault": 60
            }
          },
          {
            "id": "c7f23d54-78ca-4327-8aa5-911ee7b2c8fc",
            "name": "med_route",
            "comment": "",
            "dataType": "character",
            "default": "",
            "option": {
              "autoIncrement": false,
              "primaryKey": false,
              "unique": false,
              "notNull": false
            },
            "ui": {
              "active": false,
              "pk": false,
              "fk": false,
              "pfk": false,
              "widthName": 68.28706359863281,
              "widthComment": 60,
              "widthDataType": 60,
              "widthDefault": 60
            }
          },
          {
            "id": "27cb3bcb-64f5-4719-8009-b30bccf622e0",
            "name": "hv_discrete_dose",
            "comment": "",
            "dataType": "character",
            "default": "",
            "option": {
              "autoIncrement": false,
              "primaryKey": false,
              "unique": false,
              "notNull": false
            },
            "ui": {
              "active": false,
              "pk": false,
              "fk": false,
              "pfk": false,
              "widthName": 105.88308715820312,
              "widthComment": 60,
              "widthDataType": 60,
              "widthDefault": 60
            }
          },
          {
            "id": "fd389788-64ca-4f68-9e30-67be7433c81c",
            "name": "quantity",
            "comment": "",
            "dataType": "character",
            "default": "",
            "option": {
              "autoIncrement": false,
              "primaryKey": false,
              "unique": false,
              "notNull": false
            },
            "ui": {
              "active": false,
              "pk": false,
              "fk": false,
              "pfk": false,
              "widthName": 60,
              "widthComment": 60,
              "widthDataType": 60,
              "widthDefault": 60
            }
          },
          {
            "id": "6ac46ab5-04c5-4f19-8bb5-8f7dce0cb9a8",
            "name": "med_dis_disp_qty",
            "comment": "",
            "dataType": "numeric(18,6)",
            "default": "",
            "option": {
              "autoIncrement": false,
              "primaryKey": false,
              "unique": false,
              "notNull": false
            },
            "ui": {
              "active": false,
              "pk": false,
              "fk": false,
              "pfk": false,
              "widthName": 109.26310729980469,
              "widthComment": 60,
              "widthDataType": 86.11009216308594,
              "widthDefault": 60
            }
          },
          {
            "id": "6f600789-9d49-40de-94ff-cdfc8f316c39",
            "name": "total_doses",
            "comment": "",
            "dataType": "integer",
            "default": "",
            "option": {
              "autoIncrement": false,
              "primaryKey": false,
              "unique": false,
              "notNull": false
            },
            "ui": {
              "active": false,
              "pk": false,
              "fk": false,
              "pfk": false,
              "widthName": 71.31605529785156,
              "widthComment": 60,
              "widthDataType": 60,
              "widthDefault": 60
            }
          },
          {
            "id": "1aa2a8f0-0332-4279-aad5-ec23b8a78f8f",
            "name": "total_remaining_doses",
            "comment": "",
            "dataType": "integer",
            "default": "",
            "option": {
              "autoIncrement": false,
              "primaryKey": false,
              "unique": false,
              "notNull": false
            },
            "ui": {
              "active": false,
              "pk": false,
              "fk": false,
              "pfk": false,
              "widthName": 139.7481231689453,
              "widthComment": 60,
              "widthDataType": 60,
              "widthDefault": 60
            }
          },
          {
            "id": "2b31c87f-5216-4f4e-8105-fa7513882e4d",
            "name": "refills",
            "comment": "",
            "dataType": "character",
            "default": "",
            "option": {
              "autoIncrement": false,
              "primaryKey": false,
              "unique": false,
              "notNull": false
            },
            "ui": {
              "active": false,
              "pk": false,
              "fk": false,
              "pfk": false,
              "widthName": 60,
              "widthComment": 60,
              "widthDataType": 60,
              "widthDefault": 60
            }
          },
          {
            "id": "eb96396b-5869-4a98-8145-e0ebbf22c33d",
            "name": "instruction",
            "comment": "",
            "dataType": "integer",
            "default": "",
            "option": {
              "autoIncrement": false,
              "primaryKey": false,
              "unique": false,
              "notNull": false
            },
            "ui": {
              "active": false,
              "pk": false,
              "fk": false,
              "pfk": false,
              "widthName": 67.89707946777344,
              "widthComment": 60,
              "widthDataType": 60,
              "widthDefault": 60
            }
          },
          {
            "id": "81c6cdcc-238b-4124-9555-a7c1aa283412",
            "name": "frequency",
            "comment": "",
            "dataType": "character",
            "default": "",
            "option": {
              "autoIncrement": false,
              "primaryKey": false,
              "unique": false,
              "notNull": false
            },
            "ui": {
              "active": false,
              "pk": false,
              "fk": false,
              "pfk": false,
              "widthName": 63.17805480957031,
              "widthComment": 60,
              "widthDataType": 60,
              "widthDefault": 60
            }
          },
          {
            "id": "6453ae66-ad2c-4b9d-bd48-0d5097bec72d",
            "name": "pat_enc_date_real",
            "comment": "",
            "dataType": "numeric(18,6)",
            "default": "",
            "option": {
              "autoIncrement": false,
              "primaryKey": false,
              "unique": false,
              "notNull": false
            },
            "ui": {
              "active": false,
              "pk": false,
              "fk": false,
              "pfk": false,
              "widthName": 111.3040771484375,
              "widthComment": 60,
              "widthDataType": 86.11009216308594,
              "widthDefault": 60
            }
          },
          {
            "id": "152153a1-691e-4cf6-b053-e9586f333874",
            "name": "med_presc_prov_id",
            "comment": "",
            "dataType": "character",
            "default": "",
            "option": {
              "autoIncrement": false,
              "primaryKey": false,
              "unique": false,
              "notNull": false
            },
            "ui": {
              "active": false,
              "pk": false,
              "fk": false,
              "pfk": false,
              "widthName": 118.36311340332031,
              "widthComment": 60,
              "widthDataType": 60,
              "widthDefault": 60
            }
          },
          {
            "id": "7f081771-afb6-4c7e-bf1d-a8b917f1724b",
            "name": "gpi",
            "comment": "",
            "dataType": "character",
            "default": "",
            "option": {
              "autoIncrement": false,
              "primaryKey": false,
              "unique": false,
              "notNull": false
            },
            "ui": {
              "active": false,
              "pk": false,
              "fk": false,
              "pfk": false,
              "widthName": 60,
              "widthComment": 60,
              "widthDataType": 60,
              "widthDefault": 60
            }
          },
          {
            "id": "6d75d7d9-533e-41a4-99ae-6a1270d98a25",
            "name": "med_route_c",
            "comment": "",
            "dataType": "character",
            "default": "",
            "option": {
              "autoIncrement": false,
              "primaryKey": false,
              "unique": false,
              "notNull": false
            },
            "ui": {
              "active": false,
              "pk": false,
              "fk": false,
              "pfk": false,
              "widthName": 80.299072265625,
              "widthComment": 60,
              "widthDataType": 60,
              "widthDefault": 60
            }
          },
          {
            "id": "ecf9cb81-3893-40c6-b540-cd1f2a5cd386",
            "name": "hv_dose_unit_c",
            "comment": "",
            "dataType": "integer",
            "default": "",
            "option": {
              "autoIncrement": false,
              "primaryKey": false,
              "unique": false,
              "notNull": false
            },
            "ui": {
              "active": false,
              "pk": false,
              "fk": false,
              "pfk": false,
              "widthName": 93.72808837890625,
              "widthComment": 60,
              "widthDataType": 60,
              "widthDefault": 60
            }
          },
          {
            "id": "f50668c7-70a7-4f6e-bf5c-00726487a33c",
            "name": "max_dose_unit_c",
            "comment": "",
            "dataType": "integer",
            "default": "",
            "option": {
              "autoIncrement": false,
              "primaryKey": false,
              "unique": false,
              "notNull": false
            },
            "ui": {
              "active": false,
              "pk": false,
              "fk": false,
              "pfk": false,
              "widthName": 105.41508483886719,
              "widthComment": 60,
              "widthDataType": 60,
              "widthDefault": 60
            }
          },
          {
            "id": "19936e9d-eedc-4f72-9e2d-98d6a1b2eb29",
            "name": "order_status_c",
            "comment": "",
            "dataType": "integer",
            "default": "",
            "option": {
              "autoIncrement": false,
              "primaryKey": false,
              "unique": false,
              "notNull": false
            },
            "ui": {
              "active": false,
              "pk": false,
              "fk": false,
              "pfk": false,
              "widthName": 90.62107849121094,
              "widthComment": 60,
              "widthDataType": 60,
              "widthDefault": 60
            }
          },
          {
            "id": "a624a9d4-4fb8-4145-a31d-1a95ac6d8e70",
            "name": "hv_discr_freq_id",
            "comment": "",
            "dataType": "character",
            "default": "",
            "option": {
              "autoIncrement": false,
              "primaryKey": false,
              "unique": false,
              "notNull": false
            },
            "ui": {
              "active": false,
              "pk": false,
              "fk": false,
              "pfk": false,
              "widthName": 99.39608764648438,
              "widthComment": 60,
              "widthDataType": 60,
              "widthDefault": 60
            }
          },
          {
            "id": "95cb649f-5337-4e7c-936b-f944d6dce98d",
            "name": "pharmacy_id",
            "comment": "",
            "dataType": "integer",
            "default": "",
            "option": {
              "autoIncrement": false,
              "primaryKey": false,
              "unique": false,
              "notNull": false
            },
            "ui": {
              "active": false,
              "pk": false,
              "fk": false,
              "pfk": false,
              "widthName": 80.13006591796875,
              "widthComment": 60,
              "widthDataType": 60,
              "widthDefault": 60
            }
          },
          {
            "id": "608a51ce-39c9-4a26-b703-e608e6c13c3e",
            "name": "disp_as_written_yn",
            "comment": "",
            "dataType": "character",
            "default": "",
            "option": {
              "autoIncrement": false,
              "primaryKey": false,
              "unique": false,
              "notNull": false
            },
            "ui": {
              "active": false,
              "pk": false,
              "fk": false,
              "pfk": false,
              "widthName": 116.76409912109375,
              "widthComment": 60,
              "widthDataType": 60,
              "widthDefault": 60
            }
          },
          {
            "id": "136aeef1-459b-4bd0-b127-04338ebe8cce",
            "name": "rsn_for_discon",
            "comment": "",
            "dataType": "character",
            "default": "",
            "option": {
              "autoIncrement": false,
              "primaryKey": false,
              "unique": false,
              "notNull": false
            },
            "ui": {
              "active": false,
              "pk": false,
              "fk": false,
              "pfk": false,
              "widthName": 90.59507751464844,
              "widthComment": 60,
              "widthDataType": 60,
              "widthDefault": 60
            }
          },
          {
            "id": "823ca8e9-4499-448a-aa1c-1352bccffb06",
            "name": "ext_coverage_id",
            "comment": "",
            "dataType": "character",
            "default": "",
            "option": {
              "autoIncrement": false,
              "primaryKey": false,
              "unique": false,
              "notNull": false
            },
            "ui": {
              "active": false,
              "pk": false,
              "fk": false,
              "pfk": false,
              "widthName": 99.04507446289062,
              "widthComment": 60,
              "widthDataType": 60,
              "widthDefault": 60
            }
          },
          {
            "id": "2d585429-9f12-421c-83d8-d4ee9918a12f",
            "name": "ext_pharmacy_type",
            "comment": "",
            "dataType": "character",
            "default": "",
            "option": {
              "autoIncrement": false,
              "primaryKey": false,
              "unique": false,
              "notNull": false
            },
            "ui": {
              "active": false,
              "pk": false,
              "fk": false,
              "pfk": false,
              "widthName": 119.8450927734375,
              "widthComment": 60,
              "widthDataType": 60,
              "widthDefault": 60
            }
          },
          {
            "id": "9d0508a4-74c3-4dda-9d7b-25a4092142d8",
            "name": "ext_formulary_stat",
            "comment": "",
            "dataType": "character",
            "default": "",
            "option": {
              "autoIncrement": false,
              "primaryKey": false,
              "unique": false,
              "notNull": false
            },
            "ui": {
              "active": false,
              "pk": false,
              "fk": false,
              "pfk": false,
              "widthName": 115.63308715820312,
              "widthComment": 60,
              "widthDataType": 60,
              "widthDefault": 60
            }
          },
          {
            "id": "a451d562-86cc-434d-aa42-f96dd42ff291",
            "name": "cost",
            "comment": "",
            "dataType": "character",
            "default": "",
            "option": {
              "autoIncrement": false,
              "primaryKey": false,
              "unique": false,
              "notNull": false
            },
            "ui": {
              "active": false,
              "pk": false,
              "fk": false,
              "pfk": false,
              "widthName": 60,
              "widthComment": 60,
              "widthDataType": 60,
              "widthDefault": 60
            }
          }
        ],
        "ui": {
          "active": false,
          "left": 1455.6,
          "top": 152.5,
          "zIndex": 8,
          "widthName": 169.67416381835938,
          "widthComment": 60
        },
        "visible": true,
        "id": "7dceafdb-17ad-4945-a903-d68ced814a97"
      }
    ],
    "indexes": []
  },
  "memo": {
    "memos": [
      {
        "value": "dm - 3706\nmedications - 6,062,868\ncurrentmedications - 24,732,468\n\n\n# medications\n*ordering_dttm - seems to match encounters contact_date\n* order_start_date - seems to match encounters contact_date\n* order_end_date - NULL if current_medications has matching records\n\n# currentmedications\ncurrentmedications is larger but doesn't have everything the patient was prescribed. As titled it has only the current ones.\n* contact_date - I believe links to the envounters table The problem is for a certain patient I wasn't able to tie out the date. The encounter id though is in tact so maybe folks are getting prescriptions post encounter which makes sense.\n* ordering_dttm - seems to be the initial contact date\n* update_dttm - seems to be the latest updated time for the latest prescription. They are unique but it kind of seems like within the hours on the same day, all records have this field updated.\n\n\n",
        "ui": {
          "active": false,
          "left": 1219.017683888758,
          "top": 151.86662848916913,
          "zIndex": 1,
          "width": 201.88000285644543,
          "height": 701.2000229339607
        },
        "id": "e40a832a-3557-42c1-bd30-fe597827ce7a"
      }
    ]
  },
  "relationship": {
    "relationships": [
      {
        "identification": false,
        "relationshipType": "ZeroN",
        "startRelationshipType": "Dash",
        "start": {
          "tableId": "7dceafdb-17ad-4945-a903-d68ced814a97",
          "columnIds": [
            "16976a4b-11a1-4d9f-b040-da5598645be4"
          ],
          "x": 1910.5382171630858,
          "y": 390.125,
          "direction": "right"
        },
        "end": {
          "tableId": "c7d73d58-d408-4f7b-af3c-95283b2251c9",
          "columnIds": [
            "8949a3ff-8cac-4d31-85fc-aaa381ff06e4"
          ],
          "x": 2274.4858,
          "y": 669.5381,
          "direction": "left"
        },
        "constraintName": "fk_ophthalmologymedications_to_ophthalmologycurrentmedications",
        "visible": true,
        "id": "11a0a589-01bb-400e-89fc-28012acdfb9c"
      },
      {
        "identification": false,
        "relationshipType": "OneN",
        "startRelationshipType": "Dash",
        "start": {
          "tableId": "b04ce783-eeee-4ecc-b77f-656e1612f9b3",
          "columnIds": [
            "5839962f-5304-4f8f-9d8d-8750d8795d84"
          ],
          "x": 2276.5367,
          "y": 249.8685,
          "direction": "left"
        },
        "end": {
          "tableId": "7dceafdb-17ad-4945-a903-d68ced814a97",
          "columnIds": [
            "201069a0-313b-4da9-8cad-03bb203df61d"
          ],
          "x": 1910.5382171630858,
          "y": 865.375,
          "direction": "right"
        },
        "constraintName": "fk_ophthalmologymedicationdm_to_ophthalmologymedications",
        "visible": true,
        "id": "a8c386cd-3e95-41d3-8671-1e74668294bd"
      },
      {
        "identification": false,
        "relationshipType": "OneN",
        "startRelationshipType": "Dash",
        "start": {
          "tableId": "b04ce783-eeee-4ecc-b77f-656e1612f9b3",
          "columnIds": [
            "5839962f-5304-4f8f-9d8d-8750d8795d84"
          ],
          "x": 2485.932749499512,
          "y": 356.11850000000004,
          "direction": "bottom"
        },
        "end": {
          "tableId": "c7d73d58-d408-4f7b-af3c-95283b2251c9",
          "columnIds": [
            "1b08257c-d324-45d6-ac2d-adfe6adece74"
          ],
          "x": 2513.8818494995116,
          "y": 491.5381,
          "direction": "top"
        },
        "constraintName": "fk_ophthalmologymedicationdm_to_ophthalmologycurrentmedications",
        "visible": true,
        "id": "fa5646e1-2548-4e7d-8eb5-618f6ee65541"
      }
    ]
  }
}